MANIFEST.in
README.rst
setup.py
create_flask_app/__init__.py
create_flask_app.egg-info/PKG-INFO
create_flask_app.egg-info/SOURCES.txt
create_flask_app.egg-info/dependency_links.txt
create_flask_app.egg-info/entry_points.txt
create_flask_app.egg-info/top_level.txt
create_flask_app/template/.DS_Store
create_flask_app/template/README.rst
create_flask_app/template/manager.pyt
create_flask_app/template/requirements.txt
create_flask_app/template/setup.pyt
create_flask_app/template/__PROJECT_NAME__/.DS_Store
create_flask_app/template/__PROJECT_NAME__/__init__.pyt
create_flask_app/template/__PROJECT_NAME__/config.pyt
create_flask_app/template/__PROJECT_NAME__/router.pyt
create_flask_app/template/__PROJECT_NAME__/assets/.keep
create_flask_app/template/__PROJECT_NAME__/controller/__init__.py
create_flask_app/template/__PROJECT_NAME__/database/__init__.pyt
create_flask_app/template/__PROJECT_NAME__/static/css/.keep
create_flask_app/template/__PROJECT_NAME__/static/js/.keep
create_flask_app/template/__PROJECT_NAME__/templates/.keep