Metadata-Version: 1.1
Name: create-flask-app
Version: 0.2.1
Summary: Create flask web apps with directory layout
Home-page: https://github.com/Luavis/create-flask-app
Author: Luavis
Author-email: me@luav.is
License: MIT
Platform: POSIX
Classifier: Development Status :: 3 - Alpha
Classifier: License :: OSI Approved :: MIT License
Classifier: Environment :: Console
Classifier: Operating System :: POSIX
Classifier: Programming Language :: Python
Classifier: Programming Language :: Python :: 2.6
Classifier: Programming Language :: Python :: 2.7
Classifier: Programming Language :: Python :: 3.3
Classifier: Programming Language :: Python :: 3.4
Classifier: Programming Language :: Python :: 3.5
Classifier: Programming Language :: Python :: 3.6
